wexample_wex_core-6.0.67.dist-info/METADATA
wexample_wex_core-6.0.67.dist-info/WHEEL
wexample_wex_core-6.0.67.dist-info/entry_points.txt
wexample_wex_core/__init__.py
wexample_wex_core/__pycache__/__init__.py
wexample_wex_core/addons/__init__.py
wexample_wex_core/addons/__pycache__/__init__.py
wexample_wex_core/addons/default/__init__.py
wexample_wex_core/addons/default/__pycache__/__init__.py
wexample_wex_core/addons/default/commands/__init__.py
wexample_wex_core/addons/default/commands/info/__init__.py
wexample_wex_core/addons/default/commands/info/__pycache__/__init__.py
wexample_wex_core/addons/default/commands/info/show.py
wexample_wex_core/addons/default/commands/version/__init__.py
wexample_wex_core/addons/default/commands/version/increment.py
wexample_wex_core/addons/default/default_addon_manager.py
wexample_wex_core/addons/git/__init__.py
wexample_wex_core/addons/git/commands/__init__.py
wexample_wex_core/addons/git/commands/reset/__init__.py
wexample_wex_core/addons/git/commands/reset/permissions.py
wexample_wex_core/addons/git/git_addon_manager.py
wexample_wex_core/addons/test/__init__.py
wexample_wex_core/addons/test/commands/__init__.py
wexample_wex_core/addons/test/commands/run/__init__.py
wexample_wex_core/addons/test/commands/run/all.py
wexample_wex_core/addons/test/commands/yaml/__init__.py
wexample_wex_core/addons/test/commands/yaml/simple.yml
wexample_wex_core/addons/test/test_addon_manager.py
wexample_wex_core/addons/test/tests/__init__.py
wexample_wex_core/addons/test/tests/command/__init__.py
wexample_wex_core/command/__init__.py
wexample_wex_core/command/__pycache__/__init__.py
wexample_wex_core/command/extended_command.py
wexample_wex_core/common/__init__.py
wexample_wex_core/common/__pycache__/__init__.py
wexample_wex_core/common/abstract_addon_manager.py
wexample_wex_core/common/app_manager_kernel.py
wexample_wex_core/common/app_manager_shell_result.py
wexample_wex_core/common/command_method_wrapper.py
wexample_wex_core/common/command_request.py
wexample_wex_core/common/file/__init__.py
wexample_wex_core/common/kernel.py
wexample_wex_core/common/registry_builder.py
wexample_wex_core-6.0.67.dist-info/RECORD
