Metadata-Version: 2.1
Name: wexample-wex-core
Version: 6.0.67
Summary: Wex core
Author-Email: weeger <contact@wexample.com>
License: MIT
Classifier: Programming Language :: Python :: 3
Classifier: License :: OSI Approved :: MIT License
Classifier: Operating System :: OS Independent
Project-URL: homepage, https://github.com/wexample/wexample-wex-core
Requires-Python: >=3.10
Requires-Dist: attrs>=23.1.0
Requires-Dist: cattrs>=23.1.0
Requires-Dist: click
Requires-Dist: wexample-app==0.0.71
Requires-Dist: wexample-filestate-git==0.0.59
Requires-Dist: wexample-filestate==0.0.74
Requires-Dist: wexample-helpers-git==0.0.96
Provides-Extra: dev
Requires-Dist: pytest; extra == "dev"
Requires-Dist: pytest-cov; extra == "dev"
